LICENSE
MANIFEST.in
README.md
pyproject.toml
setup.cfg
setup.py
bin/__init__.py
bin/cythonize.py
bin/load_reddit.py
bin/spacy
bin/train_word_vectors.py
bin/ud/__init__.py
bin/ud/conll17_ud_eval.py
bin/ud/run_eval.py
bin/ud/ud_run_test.py
bin/ud/ud_train.py
include/msvc9/stdint.h
include/murmurhash/MurmurHash2.h
include/murmurhash/MurmurHash3.h
include/numpy/__multiarray_api.h
include/numpy/__ufunc_api.h
include/numpy/_neighborhood_iterator_imp.h
include/numpy/_numpyconfig.h
include/numpy/arrayobject.h
include/numpy/arrayscalars.h
include/numpy/halffloat.h
include/numpy/ndarrayobject.h
include/numpy/ndarraytypes.h
include/numpy/noprefix.h
include/numpy/npy_3kcompat.h
include/numpy/npy_common.h
include/numpy/npy_cpu.h
include/numpy/npy_deprecated_api.h
include/numpy/npy_endian.h
include/numpy/npy_interrupt.h
include/numpy/npy_math.h
include/numpy/npy_no_deprecated_api.h
include/numpy/npy_os.h
include/numpy/numpyconfig.h
include/numpy/old_defines.h
include/numpy/oldnumeric.h
include/numpy/ufuncobject.h
include/numpy/utils.h
spacy/__init__.pxd
spacy/__init__.py
spacy/__main__.py
spacy/_ml.py
spacy/about.py
spacy/analysis.py
spacy/attrs.cpp
spacy/attrs.pxd
spacy/attrs.pyx
spacy/compat.py
spacy/errors.py
spacy/glossary.py
spacy/gold.cpp
spacy/gold.pxd
spacy/gold.pyx
spacy/kb.cpp
spacy/kb.pxd
spacy/kb.pyx
spacy/language.py
spacy/lemmatizer.py
spacy/lexeme.cpp
spacy/lexeme.pxd
spacy/lexeme.pyx
spacy/logger.py
spacy/lookups.py
spacy/morphology.cpp
spacy/morphology.pxd
spacy/morphology.pyx
spacy/parts_of_speech.cpp
spacy/parts_of_speech.pxd
spacy/parts_of_speech.pyx
spacy/scorer.py
spacy/strings.cpp
spacy/strings.pxd
spacy/strings.pyx
spacy/structs.pxd
spacy/symbols.cpp
spacy/symbols.pxd
spacy/symbols.pyx
spacy/tokenizer.cpp
spacy/tokenizer.pxd
spacy/tokenizer.pyx
spacy/typedefs.pxd
spacy/typedefs.pyx
spacy/util.py
spacy/vectors.cpp
spacy/vectors.pyx
spacy/vocab.cpp
spacy/vocab.pxd
spacy/vocab.pyx
spacy/cli/__init__.py
spacy/cli/_schemas.py
spacy/cli/convert.py
spacyWB.egg-info/PKG-INFO
spacyWB.egg-info/SOURCES.txt
spacyWB.egg-info/dependency_links.txt
spacyWB.egg-info/not-zip-safe
spacyWB.egg-info/requires.txt
spacyWB.egg-info/top_level.txt